kuhl_haus/metrics/__init__.py
kuhl_haus/metrics/clients/__init__.py
kuhl_haus/metrics/clients/carbon_poster.py
kuhl_haus/metrics/data/__init__.py
kuhl_haus/metrics/data/metrics.py
kuhl_haus/metrics/env.py
kuhl_haus/metrics/factories/__init__.py
kuhl_haus/metrics/factories/logs.py
kuhl_haus/metrics/models/__init__.py
kuhl_haus/metrics/models/carbon_config.py
kuhl_haus/metrics/py.typed
kuhl_haus/metrics/recorders/__init__.py
kuhl_haus/metrics/recorders/graphite_logger.py
kuhl_haus/metrics/tasks/__init__.py
kuhl_haus/metrics/tasks/thread_pool.py
kuhl_haus_metrics-0.2.22.dist-info/METADATA
kuhl_haus_metrics-0.2.22.dist-info/WHEEL
kuhl_haus_metrics-0.2.22.dist-info/entry_points.txt
kuhl_haus_metrics-0.2.22.dist-info/licenses/LICENSE.txt
kuhl_haus_metrics-0.2.22.dist-info/RECORD
