Metadata-Version: 2.1
Name: kuhl-haus-metrics
Version: 0.2.22
Summary: Application logging and instrumentation
Author-Email: Tom Pounders <git@oldschool.engineer>
License: The MIT License (MIT)
Classifier: Development Status :: 4 - Beta
Classifier: Programming Language :: Python
Project-URL: Homepage, https://github.com/kuhl-haus
Project-URL: Documentation, https://github.com/kuhl-haus/kuhl-haus-metrics/wiki
Project-URL: Source, https://github.com/kuhl-haus/kuhl-haus-metrics.git
Project-URL: Changelog, https://github.com/kuhl-haus/kuhl-haus-metrics/commits
Project-URL: Tracker, https://github.com/kuhl-haus/kuhl-haus-metrics/issues
Requires-Python: >=3.12
Requires-Dist: fastapi
Requires-Dist: importlib_metadata
Requires-Dist: dataclasses-json
Requires-Dist: importlib-metadata
Provides-Extra: testing
Requires-Dist: setuptools; extra == "testing"
Requires-Dist: pdm-backend; extra == "testing"
Requires-Dist: pytest; extra == "testing"
Requires-Dist: pytest-cov; extra == "testing"
Requires-Dist: pytest-asyncio; extra == "testing"
Requires-Dist: httpx; extra == "testing"
Requires-Dist: starlette; extra == "testing"
